[{"__symbolic":"module","version":4,"metadata":{"NavbarControl":{"__symbolic":"class","decorators":[{"__symbolic":"call","expression":{"__symbolic":"reference","module":"@angular/core","name":"Component","line":4,"character":1},"arguments":[{"selector":"market-navbar","host":{"class":"navbar","$quoted$":["class"]},"templateUrl":"navbar.html"}]}],"members":{"__ctor__":[{"__symbolic":"constructor","parameters":[{"__symbolic":"reference","module":"services/index","name":"NavbarService","line":45,"character":39}]}]}}}}]